hpsv2/__init__.py
hpsv2/evaluation.py
hpsv2/img_score.py
hpsv2/utils.py
hpsv2/assets/demo_image.jpg
hpsv2/assets/hps_banner.png
hpsv2/assets/overview.png
hpsv2/assets/test_vis.png
hpsv2/configs/HPSv2.sh
hpsv2/configs/controller.sh
hpsv2/src/__init__.py
hpsv2/src/open_clip/__init__.py
hpsv2/src/open_clip/coca_model.py
hpsv2/src/open_clip/constants.py
hpsv2/src/open_clip/factory.py
hpsv2/src/open_clip/generation_utils.py
hpsv2/src/open_clip/hf_configs.py
hpsv2/src/open_clip/hf_model.py
hpsv2/src/open_clip/loss.py
hpsv2/src/open_clip/model.py
hpsv2/src/open_clip/modified_resnet.py
hpsv2/src/open_clip/openai.py
hpsv2/src/open_clip/pretrained.py
hpsv2/src/open_clip/push_to_hf_hub.py
hpsv2/src/open_clip/timm_model.py
hpsv2/src/open_clip/tokenizer.py
hpsv2/src/open_clip/transform.py
hpsv2/src/open_clip/transformer.py
hpsv2/src/open_clip/utils.py
hpsv2/src/open_clip/version.py
hpsv2/src/open_clip/model_configs/RN101-quickgelu.json
hpsv2/src/open_clip/model_configs/RN101.json
hpsv2/src/open_clip/model_configs/RN50-quickgelu.json
hpsv2/src/open_clip/model_configs/RN50.json
hpsv2/src/open_clip/model_configs/RN50x16.json
hpsv2/src/open_clip/model_configs/RN50x4.json
hpsv2/src/open_clip/model_configs/RN50x64.json
hpsv2/src/open_clip/model_configs/ViT-B-16-plus-240.json
hpsv2/src/open_clip/model_configs/ViT-B-16-plus.json
hpsv2/src/open_clip/model_configs/ViT-B-16.json
hpsv2/src/open_clip/model_configs/ViT-B-32-plus-256.json
hpsv2/src/open_clip/model_configs/ViT-B-32-quickgelu.json
hpsv2/src/open_clip/model_configs/ViT-B-32.json
hpsv2/src/open_clip/model_configs/ViT-H-14.json
hpsv2/src/open_clip/model_configs/ViT-H-16.json
hpsv2/src/open_clip/model_configs/ViT-L-14-280.json
hpsv2/src/open_clip/model_configs/ViT-L-14-336.json
hpsv2/src/open_clip/model_configs/ViT-L-14.json
hpsv2/src/open_clip/model_configs/ViT-L-16-320.json
hpsv2/src/open_clip/model_configs/ViT-L-16.json
hpsv2/src/open_clip/model_configs/ViT-M-16-alt.json
hpsv2/src/open_clip/model_configs/ViT-M-16.json
hpsv2-1.2.0.dist-info/LICENSE
hpsv2-1.2.0.dist-info/METADATA
hpsv2-1.2.0.dist-info/WHEEL
hpsv2-1.2.0.dist-info/top_level.txt
hpsv2-1.2.0.dist-info/RECORD
