Metadata-Version: 2.1
Name: hpsv2
Version: 1.2.0
Summary: Human Preference Score v2: A Solid Benchmark for Evaluating Human Preferences of Text-to-Image Synthesis.
Home-page: https://github.com/tgxs002/HPSv2
Author: Zhiheng Wang et al.
Author-email: wangzhih02@gmail.com
License: Apache License 2.0
Platform: UNKNOWN
Classifier: License :: OSI Approved :: Apache Software License
Classifier: Programming Language :: Python
Classifier: Programming Language :: Python :: 3
Classifier: Programming Language :: Python :: 3.6
Classifier: Programming Language :: Python :: Implementation :: CPython
Classifier: Programming Language :: Python :: Implementation :: PyPy
Requires-Python: >=3.6.0
Requires-Dist: torch >=1.9.0
Requires-Dist: torchvision
Requires-Dist: regex
Requires-Dist: ftfy
Requires-Dist: einops
Requires-Dist: pandas
Requires-Dist: braceexpand
Requires-Dist: fsspec
Requires-Dist: tqdm
Requires-Dist: huggingface-hub
Requires-Dist: sentencepiece
Requires-Dist: protobuf <4
Requires-Dist: timm
Requires-Dist: transformers
Requires-Dist: webdataset
Requires-Dist: pyarrow
Requires-Dist: pytest-split ==0.8.0
Requires-Dist: pytest ==7.2.0
Requires-Dist: requests
Requires-Dist: clint
